gspack/__about__.py
gspack/__init__.py
gspack/directories.py
gspack/environment.py
gspack/executor.py
gspack/grader.py
gspack/helpers.py
gspack/matlab_executor.py
gspack/packager.py
gspack/rubric.py
gspack/templates/gs_debug.sh
gspack/templates/run_autograder
gspack/templates/setup.sh
gspack-0.2.10.dist-info/LICENSE
gspack-0.2.10.dist-info/METADATA
gspack-0.2.10.dist-info/WHEEL
gspack-0.2.10.dist-info/entry_points.txt
gspack-0.2.10.dist-info/top_level.txt
gspack-0.2.10.dist-info/RECORD
